pythonik_ext-2025.4.2b0.dist-info/licenses/LICENSE
pythonikext/__init__.py
pythonikext/__version__.py
pythonikext/_internal_utils.py
pythonikext/_logging.py
pythonikext/client.py
pythonikext/exceptions.py
pythonikext/utils.py
pythonikext/recipes/__init__.py
pythonikext/recipes/collection_directory_mapping.py
pythonikext/recipes/file_ingest.py
pythonikext/specs/__init__.py
pythonikext/specs/assets.py
pythonikext/specs/base.py
pythonikext/specs/collection.py
pythonikext/specs/files.py
pythonikext/specs/jobs.py
pythonikext/specs/metadata.py
pythonikext/specs/search.py
pythonik_ext-2025.4.2b0.dist-info/METADATA
pythonik_ext-2025.4.2b0.dist-info/WHEEL
pythonik_ext-2025.4.2b0.dist-info/top_level.txt
pythonik_ext-2025.4.2b0.dist-info/RECORD
