Metadata-Version: 2.4
Name: pythonik-ext
Version: 2025.4.2b0
Summary: Extensions and enhancements for the pythonik client library
Author-email: Brian Summa <brian.f.summa@chesa.com>
License: MIT
Project-URL: Homepage, https://github.com/briansumma/pythonik-ext
Project-URL: Issues, https://github.com/briansumma/pythonik-ext/issues
Keywords: iconik,api,pythonik,extensions
Classifier: Development Status :: 4 - Beta
Classifier: Intended Audience :: Developers
Classifier: License :: OSI Approved :: MIT License
Classifier: Programming Language :: Python :: 3
Classifier: Programming Language :: Python :: 3.11
Classifier: Programming Language :: Python :: 3.12
Requires-Python: >=3.11
License-File: LICENSE
Requires-Dist: nsa-pythonik==1.9.4
Provides-Extra: dev
Requires-Dist: ruff~=0.11.2; extra == "dev"
Requires-Dist: pylint~=3.3.6; extra == "dev"
Requires-Dist: yapf~=0.43.0; extra == "dev"
Requires-Dist: isort~=5.13.2; extra == "dev"
Requires-Dist: pytest~=7.4.0; extra == "dev"
Requires-Dist: build~=1.0.3; extra == "dev"
Requires-Dist: twine~=4.0.2; extra == "dev"
Requires-Dist: python-json-logger==3.3.0; extra == "dev"
Provides-Extra: logging
Requires-Dist: python-json-logger==3.3.0; extra == "logging"
Provides-Extra: all
Requires-Dist: ruff~=0.11.2; extra == "all"
Requires-Dist: pylint~=3.3.6; extra == "all"
Requires-Dist: yapf~=0.43.0; extra == "all"
Requires-Dist: isort~=5.13.2; extra == "all"
Requires-Dist: pytest~=7.4.0; extra == "all"
Requires-Dist: build~=1.0.3; extra == "all"
Requires-Dist: twine~=4.0.2; extra == "all"
Requires-Dist: python-json-logger==3.3.0; extra == "all"
Dynamic: license-file
